{
  "version": "2026-04-24T13:02:03.761Z",
  "items": [
    {
      "id": "blocks/display/gradient-stat-card",
      "type": "block",
      "name": "渐变图标统计卡",
      "description": "运营概览专用——icon 独占右侧 42×42 渐变圆角底 + 色阴影 + 左侧大号数字",
      "platforms": [
        "web"
      ],
      "theme": "light",
      "tags": {
        "aesthetic": [
          "minimal",
          "editorial"
        ],
        "mood": [
          "calm",
          "confident"
        ],
        "stack": [
          "react-antd-tailwind"
        ]
      },
      "uses": [
        "tokens/palettes/skillhub-teal-mist",
        "tokens/shadow/ambient-float"
      ],
      "preview": "/preview/blocks/display/gradient-stat-card",
      "usedBy": [
        "styles/community-social/skillhub-soft-modernist",
        "pages/dashboard/admin-overview"
      ],
      "hasPreviewFile": true,
      "skillPath": "blocks/display/gradient-stat-card.md"
    },
    {
      "id": "blocks/display/leaderboard-row",
      "type": "block",
      "name": "榜单行",
      "description": "4 列网格榜单行——#秩 / 名称+描述 / 分类 pill / stats；Top3 用红黄蓝高亮",
      "platforms": [
        "web"
      ],
      "theme": "light",
      "tags": {
        "aesthetic": [
          "minimal",
          "editorial"
        ],
        "mood": [
          "calm",
          "confident"
        ],
        "stack": [
          "react-antd-tailwind"
        ]
      },
      "uses": [
        "tokens/palettes/skillhub-teal-mist",
        "tokens/motion/gentle-flow",
        "components/avatars-icons/letter-avatar",
        "components/tags-badges/teal-pill"
      ],
      "preview": "/preview/blocks/display/leaderboard-row",
      "usedBy": [
        "styles/community-social/skillhub-soft-modernist",
        "pages/landing/skill-community-home",
        "pages/list-table/practice-plaza"
      ],
      "hasPreviewFile": true,
      "skillPath": "blocks/display/leaderboard-row.md"
    },
    {
      "id": "blocks/display/skill-card",
      "type": "block",
      "name": "Skill 卡片",
      "description": "字母头像 + 版本胶囊 + 3 项 stats + 底部分隔线 + hover 边框变 teal + y:-4 浮起",
      "platforms": [
        "web"
      ],
      "theme": "light",
      "tags": {
        "aesthetic": [
          "minimal",
          "editorial"
        ],
        "mood": [
          "calm",
          "confident"
        ],
        "stack": [
          "react-antd-tailwind"
        ]
      },
      "uses": [
        "tokens/palettes/skillhub-teal-mist",
        "tokens/shadow/ambient-float",
        "tokens/motion/gentle-flow",
        "components/avatars-icons/letter-avatar"
      ],
      "preview": "/preview/blocks/display/skill-card",
      "usedBy": [
        "styles/community-social/skillhub-soft-modernist",
        "pages/dashboard/user-home",
        "pages/landing/skill-community-home"
      ],
      "hasPreviewFile": true,
      "skillPath": "blocks/display/skill-card.md"
    },
    {
      "id": "blocks/display/table",
      "type": "block",
      "name": "管理后台表格",
      "description": "管理后台无边框表格，统一分页、中文本地化、行 hover 减淡",
      "platforms": [
        "web"
      ],
      "theme": "light",
      "tags": {
        "aesthetic": [
          "minimal"
        ],
        "mood": [
          "calm",
          "serious"
        ],
        "stack": [
          "react-antd-tailwind"
        ]
      },
      "uses": [],
      "preview": "/preview/blocks/display/table",
      "usedBy": [
        "blocks/layout/toolbar-bar",
        "styles/community-social/skillhub-soft-modernist",
        "pages/list-table/admin-console"
      ],
      "hasPreviewFile": true,
      "skillPath": "blocks/display/table.md"
    },
    {
      "id": "blocks/feedback/empty-state",
      "type": "block",
      "name": "空态",
      "description": "虚线容器 + 灰色 icon + 标题 + 一行提示，无 CTA 的克制空态",
      "platforms": [
        "web"
      ],
      "theme": "light",
      "tags": {
        "aesthetic": [
          "minimal",
          "editorial"
        ],
        "mood": [
          "calm",
          "confident"
        ],
        "stack": [
          "react-antd-tailwind"
        ]
      },
      "uses": [
        "tokens/palettes/skillhub-teal-mist"
      ],
      "preview": "/preview/blocks/feedback/empty-state",
      "usedBy": [
        "styles/community-social/skillhub-soft-modernist",
        "pages/dashboard/user-home",
        "pages/list-table/practice-plaza"
      ],
      "hasPreviewFile": true,
      "skillPath": "blocks/feedback/empty-state.md"
    },
    {
      "id": "blocks/feedback/skeleton-card",
      "type": "block",
      "name": "骨架卡片",
      "description": "和 skill-card / 其它主卡等尺寸的 animate-pulse 骨架占位",
      "platforms": [
        "web"
      ],
      "theme": "light",
      "tags": {
        "aesthetic": [
          "minimal",
          "editorial"
        ],
        "mood": [
          "calm",
          "confident"
        ],
        "stack": [
          "react-antd-tailwind"
        ]
      },
      "uses": [
        "tokens/palettes/skillhub-teal-mist",
        "tokens/motion/gentle-flow"
      ],
      "preview": "/preview/blocks/feedback/skeleton-card",
      "usedBy": [
        "styles/community-social/skillhub-soft-modernist"
      ],
      "hasPreviewFile": true,
      "skillPath": "blocks/feedback/skeleton-card.md"
    },
    {
      "id": "blocks/form/auth-split-form",
      "type": "block",
      "name": "分屏登录注册表单",
      "description": "两屏切换（密码 / 注册）+ slate 渐变方块 logo + soft-form-input 字段 + dark CTA",
      "platforms": [
        "web"
      ],
      "theme": "light",
      "tags": {
        "aesthetic": [
          "minimal",
          "editorial"
        ],
        "mood": [
          "calm",
          "confident"
        ],
        "stack": [
          "react-antd-tailwind"
        ]
      },
      "uses": [
        "tokens/palettes/skillhub-teal-mist",
        "tokens/typography/pairs/inter-jetbrains-duo",
        "components/inputs/soft-form-input",
        "components/buttons/dark-primary-cta"
      ],
      "preview": "/preview/blocks/form/auth-split-form",
      "usedBy": [
        "styles/community-social/skillhub-soft-modernist",
        "pages/auth/auth-split"
      ],
      "hasPreviewFile": true,
      "skillPath": "blocks/form/auth-split-form.md"
    },
    {
      "id": "blocks/form/profile-edit-form",
      "type": "block",
      "name": "资料编辑表单",
      "description": "iOS 风列表点击编辑——每行 [label · value · ChevronRight]，点击弹独立 modal 修改",
      "platforms": [
        "web"
      ],
      "theme": "light",
      "tags": {
        "aesthetic": [
          "minimal",
          "editorial"
        ],
        "mood": [
          "calm",
          "confident"
        ],
        "stack": [
          "react-antd-tailwind"
        ]
      },
      "uses": [
        "tokens/palettes/skillhub-teal-mist",
        "components/avatars-icons/letter-avatar"
      ],
      "preview": "/preview/blocks/form/profile-edit-form",
      "usedBy": [
        "styles/community-social/skillhub-soft-modernist",
        "pages/form-flow/profile-edit"
      ],
      "hasPreviewFile": true,
      "skillPath": "blocks/form/profile-edit-form.md"
    },
    {
      "id": "blocks/layout/toolbar-bar",
      "type": "block",
      "name": "管理后台工具栏",
      "description": "表格顶部工具栏，搜索+筛选左对齐，功能按钮右对齐",
      "platforms": [
        "web"
      ],
      "theme": "light",
      "tags": {
        "aesthetic": [
          "minimal"
        ],
        "mood": [
          "calm",
          "serious"
        ],
        "stack": [
          "react-antd-tailwind"
        ]
      },
      "uses": [
        "blocks/display/table"
      ],
      "preview": "/preview/blocks/layout/toolbar-bar",
      "usedBy": [
        "styles/community-social/skillhub-soft-modernist",
        "pages/list-table/admin-console"
      ],
      "hasPreviewFile": true,
      "skillPath": "blocks/layout/toolbar-bar.md"
    },
    {
      "id": "blocks/marketing/gradient-hero",
      "type": "block",
      "name": "流光渐变 Hero",
      "description": "超大号 Hero 标题 + 某一强调词用 4 色流动渐变 + 双 CTA（追光主 + ghost 次）",
      "platforms": [
        "web"
      ],
      "theme": "light",
      "tags": {
        "aesthetic": [
          "minimal",
          "editorial"
        ],
        "mood": [
          "calm",
          "confident"
        ],
        "stack": [
          "react-antd-tailwind"
        ]
      },
      "uses": [
        "tokens/palettes/skillhub-teal-mist",
        "tokens/typography/pairs/inter-jetbrains-duo",
        "tokens/motion/gentle-flow",
        "components/buttons/border-trace-cta"
      ],
      "preview": "/preview/blocks/marketing/gradient-hero",
      "usedBy": [
        "styles/community-social/skillhub-soft-modernist",
        "pages/landing/skill-community-home"
      ],
      "hasPreviewFile": true,
      "skillPath": "blocks/marketing/gradient-hero.md"
    },
    {
      "id": "blocks/nav/glass-pill-navbar",
      "type": "block",
      "name": "玻璃 Pill 导航栏",
      "description": "玻璃层 + 内嵌白色圆角 pill + 3 列 grid（品牌 / 中心导航 / 鉴权）",
      "platforms": [
        "web"
      ],
      "theme": "light",
      "tags": {
        "aesthetic": [
          "minimal",
          "editorial"
        ],
        "mood": [
          "calm",
          "confident"
        ],
        "stack": [
          "react-antd-tailwind"
        ]
      },
      "uses": [
        "tokens/palettes/skillhub-teal-mist",
        "tokens/shadow/ambient-float"
      ],
      "preview": "/preview/blocks/nav/glass-pill-navbar",
      "usedBy": [
        "styles/community-social/skillhub-soft-modernist",
        "pages/content-reader/im-conversation",
        "pages/dashboard/admin-overview",
        "pages/dashboard/user-home",
        "pages/detail/practice-post-detail",
        "pages/form-flow/practice-compose",
        "pages/detail/user-public-profile",
        "pages/form-flow/profile-edit",
        "pages/landing/skill-community-home",
        "pages/list-table/admin-console",
        "pages/list-table/practice-plaza",
        "pages/form-flow/skill-publish-wizard"
      ],
      "hasPreviewFile": true,
      "skillPath": "blocks/nav/glass-pill-navbar.md"
    },
    {
      "id": "components/avatars-icons/letter-avatar",
      "type": "component",
      "name": "12 色柔和字母头像",
      "description": "基于 index 的 12 色柔和轮转底色 + 白色粗体首字母的圆形头像",
      "platforms": [
        "web"
      ],
      "theme": "light",
      "tags": {
        "aesthetic": [
          "minimal",
          "editorial"
        ],
        "mood": [
          "calm",
          "confident"
        ],
        "stack": [
          "react-antd-tailwind"
        ]
      },
      "uses": [
        "tokens/palettes/skillhub-teal-mist"
      ],
      "preview": "/preview/components/avatars-icons/letter-avatar",
      "usedBy": [
        "blocks/display/leaderboard-row",
        "blocks/display/skill-card",
        "blocks/form/profile-edit-form",
        "styles/community-social/skillhub-soft-modernist",
        "pages/content-reader/im-conversation",
        "pages/dashboard/user-home",
        "pages/detail/practice-post-detail",
        "pages/detail/user-public-profile",
        "pages/landing/skill-community-home",
        "pages/list-table/practice-plaza",
        "pages/detail/skill-article-detail"
      ],
      "hasPreviewFile": true,
      "skillPath": "components/avatars-icons/letter-avatar.md"
    },
    {
      "id": "components/buttons/border-trace-cta",
      "type": "component",
      "name": "追光边框 CTA",
      "description": "黑底 CTA 外缘跑 SVG 双环追光（cyan 主线 + purple 副线），品牌级召唤按钮",
      "platforms": [
        "web"
      ],
      "theme": "light",
      "tags": {
        "aesthetic": [
          "minimal",
          "editorial"
        ],
        "mood": [
          "calm",
          "confident"
        ],
        "stack": [
          "react-antd-tailwind"
        ]
      },
      "uses": [
        "tokens/palettes/skillhub-teal-mist",
        "tokens/motion/gentle-flow"
      ],
      "preview": "/preview/components/buttons/border-trace-cta",
      "usedBy": [
        "blocks/marketing/gradient-hero",
        "styles/community-social/skillhub-soft-modernist"
      ],
      "hasPreviewFile": true,
      "skillPath": "components/buttons/border-trace-cta.md"
    },
    {
      "id": "components/buttons/dark-primary-cta",
      "type": "component",
      "name": "黑底主 CTA",
      "description": "全站统一的黑底 CTA（#1a1a1a / slate-900）+ active:scale-95 + hover:bg-[#333] 的黑白按钮骨架",
      "platforms": [
        "web"
      ],
      "theme": "light",
      "tags": {
        "aesthetic": [
          "minimal",
          "editorial"
        ],
        "mood": [
          "calm",
          "confident"
        ],
        "stack": [
          "react-antd-tailwind"
        ]
      },
      "uses": [
        "tokens/palettes/skillhub-teal-mist"
      ],
      "preview": "/preview/components/buttons/dark-primary-cta",
      "usedBy": [
        "blocks/form/auth-split-form",
        "styles/community-social/skillhub-soft-modernist",
        "pages/content-reader/im-conversation",
        "pages/dashboard/user-home",
        "pages/detail/practice-post-detail",
        "pages/form-flow/practice-compose",
        "pages/detail/user-public-profile",
        "pages/form-flow/profile-edit",
        "pages/list-table/practice-plaza",
        "pages/form-flow/skill-publish-wizard"
      ],
      "hasPreviewFile": true,
      "skillPath": "components/buttons/dark-primary-cta.md"
    },
    {
      "id": "components/buttons/ghost-button",
      "type": "component",
      "name": "幽灵按钮",
      "description": "幽灵按钮——透明底 + 1px 描边，只在 hover 时显色",
      "platforms": [
        "web"
      ],
      "theme": "both",
      "tags": {
        "aesthetic": [
          "minimal",
          "industrial"
        ],
        "mood": [
          "calm",
          "serious"
        ],
        "stack": [
          "react-antd-tailwind",
          "html-tailwind"
        ]
      },
      "uses": [
        "tokens/palettes/slate-cyan-ice"
      ],
      "preview": "/preview/components/buttons/ghost-button",
      "usedBy": [
        "styles/saas-tool/cold-industrial-saas"
      ],
      "hasPreviewFile": true,
      "skillPath": "components/buttons/ghost-button.md"
    },
    {
      "id": "components/indicators/pulse-dot",
      "type": "component",
      "name": "脉冲状态点",
      "description": "6-8px 圆点 + 颜色辉光 + animate-pulse 的状态指示器",
      "platforms": [
        "web"
      ],
      "theme": "light",
      "tags": {
        "aesthetic": [
          "minimal",
          "editorial"
        ],
        "mood": [
          "calm",
          "confident"
        ],
        "stack": [
          "react-antd-tailwind"
        ]
      },
      "uses": [
        "tokens/palettes/skillhub-teal-mist",
        "tokens/shadow/ambient-float"
      ],
      "preview": "/preview/components/indicators/pulse-dot",
      "usedBy": [
        "styles/community-social/skillhub-soft-modernist",
        "pages/content-reader/im-conversation"
      ],
      "hasPreviewFile": true,
      "skillPath": "components/indicators/pulse-dot.md"
    },
    {
      "id": "components/inputs/soft-form-input",
      "type": "component",
      "name": "柔边表单输入",
      "description": "统一的表单级输入——slate-300 边 + rounded-xl + primary-500/20 focus ring",
      "platforms": [
        "web"
      ],
      "theme": "light",
      "tags": {
        "aesthetic": [
          "minimal",
          "editorial"
        ],
        "mood": [
          "calm",
          "confident"
        ],
        "stack": [
          "react-antd-tailwind"
        ]
      },
      "uses": [
        "tokens/palettes/skillhub-teal-mist"
      ],
      "preview": "/preview/components/inputs/soft-form-input",
      "usedBy": [
        "blocks/form/auth-split-form",
        "styles/community-social/skillhub-soft-modernist",
        "pages/content-reader/im-conversation",
        "pages/form-flow/practice-compose",
        "pages/form-flow/skill-publish-wizard"
      ],
      "hasPreviewFile": true,
      "skillPath": "components/inputs/soft-form-input.md"
    },
    {
      "id": "components/tags-badges/teal-pill",
      "type": "component",
      "name": "Teal 胶囊标签",
      "description": "圆角 full 的 teal 系分类标签，用于 skill 分类 / 版本号等轻量元信息",
      "platforms": [
        "web"
      ],
      "theme": "light",
      "tags": {
        "aesthetic": [
          "minimal",
          "editorial"
        ],
        "mood": [
          "calm",
          "confident"
        ],
        "stack": [
          "react-antd-tailwind"
        ]
      },
      "uses": [
        "tokens/palettes/skillhub-teal-mist"
      ],
      "preview": "/preview/components/tags-badges/teal-pill",
      "usedBy": [
        "blocks/display/leaderboard-row",
        "styles/community-social/skillhub-soft-modernist",
        "pages/detail/practice-post-detail",
        "pages/form-flow/practice-compose",
        "pages/detail/user-public-profile",
        "pages/landing/skill-community-home",
        "pages/list-table/practice-plaza"
      ],
      "hasPreviewFile": true,
      "skillPath": "components/tags-badges/teal-pill.md"
    },
    {
      "id": "pages/auth/auth-split",
      "type": "page",
      "name": "登录注册分屏",
      "description": "左表单 / 右视觉（slate 渐变 + slogan）的经典双栏登录页",
      "platforms": [
        "web"
      ],
      "theme": "light",
      "tags": {
        "aesthetic": [
          "minimal",
          "editorial"
        ],
        "mood": [
          "calm",
          "confident"
        ],
        "stack": [
          "react-antd-tailwind"
        ]
      },
      "uses": [
        "blocks/form/auth-split-form",
        "tokens/palettes/skillhub-teal-mist",
        "tokens/typography/pairs/inter-jetbrains-duo"
      ],
      "preview": "/preview/pages/auth/auth-split",
      "usedBy": [
        "styles/community-social/skillhub-soft-modernist"
      ],
      "hasPreviewFile": true,
      "skillPath": "pages/auth/auth-split/README.md"
    },
    {
      "id": "pages/content-reader/im-conversation",
      "type": "page",
      "name": "消息会话",
      "description": "左会话列表 + 右消息流的经典 IM 布局，带搜索 / 未读 / 气泡区分自己对方",
      "platforms": [
        "web"
      ],
      "theme": "light",
      "tags": {
        "aesthetic": [
          "minimal",
          "editorial"
        ],
        "mood": [
          "calm",
          "confident"
        ],
        "stack": [
          "react-antd-tailwind"
        ]
      },
      "uses": [
        "blocks/nav/glass-pill-navbar",
        "components/avatars-icons/letter-avatar",
        "components/indicators/pulse-dot",
        "components/buttons/dark-primary-cta",
        "components/inputs/soft-form-input",
        "tokens/palettes/skillhub-teal-mist"
      ],
      "preview": "/preview/pages/content-reader/im-conversation",
      "usedBy": [
        "styles/community-social/skillhub-soft-modernist"
      ],
      "hasPreviewFile": true,
      "skillPath": "pages/content-reader/im-conversation/README.md"
    },
    {
      "id": "pages/dashboard/admin-overview",
      "type": "page",
      "name": "运营概览页",
      "description": "管理后台 overview tab 独立成页——4 格渐变 stat card + 数据分布条 + 趋势迷你卡",
      "platforms": [
        "web"
      ],
      "theme": "light",
      "tags": {
        "aesthetic": [
          "minimal",
          "editorial"
        ],
        "mood": [
          "calm",
          "confident"
        ],
        "stack": [
          "react-antd-tailwind"
        ]
      },
      "uses": [
        "blocks/nav/glass-pill-navbar",
        "blocks/display/gradient-stat-card",
        "tokens/palettes/skillhub-teal-mist",
        "tokens/typography/pairs/inter-jetbrains-duo"
      ],
      "preview": "/preview/pages/dashboard/admin-overview",
      "usedBy": [
        "styles/community-social/skillhub-soft-modernist"
      ],
      "hasPreviewFile": true,
      "skillPath": "pages/dashboard/admin-overview/README.md"
    },
    {
      "id": "pages/dashboard/user-home",
      "type": "page",
      "name": "用户中心主页",
      "description": "顶部用户卡 + 操作区 + Tabs（我的技能 / 实践 / 点赞 / 收藏 / 投稿记录 / 关注）",
      "platforms": [
        "web"
      ],
      "theme": "light",
      "tags": {
        "aesthetic": [
          "minimal",
          "editorial"
        ],
        "mood": [
          "calm",
          "confident"
        ],
        "stack": [
          "react-antd-tailwind"
        ]
      },
      "uses": [
        "blocks/nav/glass-pill-navbar",
        "blocks/display/skill-card",
        "blocks/feedback/empty-state",
        "components/buttons/dark-primary-cta",
        "components/avatars-icons/letter-avatar",
        "tokens/palettes/skillhub-teal-mist"
      ],
      "preview": "/preview/pages/dashboard/user-home",
      "usedBy": [
        "styles/community-social/skillhub-soft-modernist"
      ],
      "hasPreviewFile": true,
      "skillPath": "pages/dashboard/user-home/README.md"
    },
    {
      "id": "pages/detail/practice-post-detail",
      "type": "page",
      "name": "实践帖详情页",
      "description": "单栏长文 + 顶部元信息（作者/时间/关联 skill）+ 底部互动 + 评论",
      "platforms": [
        "web"
      ],
      "theme": "light",
      "tags": {
        "aesthetic": [
          "minimal",
          "editorial"
        ],
        "mood": [
          "calm",
          "confident"
        ],
        "stack": [
          "react-antd-tailwind"
        ]
      },
      "uses": [
        "blocks/nav/glass-pill-navbar",
        "components/avatars-icons/letter-avatar",
        "components/buttons/dark-primary-cta",
        "components/tags-badges/teal-pill",
        "tokens/typography/pairs/inter-jetbrains-duo"
      ],
      "preview": "/preview/pages/detail/practice-post-detail",
      "usedBy": [
        "styles/community-social/skillhub-soft-modernist"
      ],
      "hasPreviewFile": true,
      "skillPath": "pages/detail/practice-post-detail/README.md"
    },
    {
      "id": "pages/detail/skill-article-detail",
      "type": "page",
      "name": "Skill 技能详情页",
      "description": "顶部 breadcrumb + 安装命令条 + SUMMARY box + SKILL.md 文档 + 280px 元信息 sidebar + timeline 评论区",
      "platforms": [
        "web"
      ],
      "theme": "light",
      "tags": {
        "aesthetic": [
          "minimal",
          "editorial"
        ],
        "mood": [
          "calm",
          "confident"
        ],
        "stack": [
          "react-antd-tailwind"
        ]
      },
      "uses": [
        "components/avatars-icons/letter-avatar",
        "tokens/palettes/skillhub-teal-mist",
        "tokens/typography/pairs/inter-jetbrains-duo"
      ],
      "preview": "/preview/pages/detail/skill-article-detail",
      "usedBy": [
        "styles/community-social/skillhub-soft-modernist"
      ],
      "hasPreviewFile": true,
      "skillPath": "pages/detail/skill-article-detail/README.md"
    },
    {
      "id": "pages/detail/user-public-profile",
      "type": "page",
      "name": "用户公开主页",
      "description": "浏览他人主页——大 hero 头像 + 关注按钮 + 实践列表 + 相关技能",
      "platforms": [
        "web"
      ],
      "theme": "light",
      "tags": {
        "aesthetic": [
          "minimal",
          "editorial"
        ],
        "mood": [
          "calm",
          "confident"
        ],
        "stack": [
          "react-antd-tailwind"
        ]
      },
      "uses": [
        "blocks/nav/glass-pill-navbar",
        "components/buttons/dark-primary-cta",
        "components/avatars-icons/letter-avatar",
        "components/tags-badges/teal-pill",
        "tokens/palettes/skillhub-teal-mist"
      ],
      "preview": "/preview/pages/detail/user-public-profile",
      "usedBy": [
        "styles/community-social/skillhub-soft-modernist"
      ],
      "hasPreviewFile": true,
      "skillPath": "pages/detail/user-public-profile/README.md"
    },
    {
      "id": "pages/form-flow/practice-compose",
      "type": "page",
      "name": "实践帖发布编辑器",
      "description": "大标题输入 + 关联 skill 多选 + Markdown 编辑器 + 预览切换 + 发布 CTA",
      "platforms": [
        "web"
      ],
      "theme": "light",
      "tags": {
        "aesthetic": [
          "minimal",
          "editorial"
        ],
        "mood": [
          "calm",
          "confident"
        ],
        "stack": [
          "react-antd-tailwind"
        ]
      },
      "uses": [
        "blocks/nav/glass-pill-navbar",
        "components/buttons/dark-primary-cta",
        "components/inputs/soft-form-input",
        "components/tags-badges/teal-pill",
        "tokens/typography/pairs/inter-jetbrains-duo"
      ],
      "preview": "/preview/pages/form-flow/practice-compose",
      "usedBy": [
        "styles/community-social/skillhub-soft-modernist"
      ],
      "hasPreviewFile": true,
      "skillPath": "pages/form-flow/practice-compose/README.md"
    },
    {
      "id": "pages/form-flow/profile-edit",
      "type": "page",
      "name": "编辑资料页",
      "description": "单栏长表单（头像 section + 基本信息 section + 危险区），顶部返回 + 保存",
      "platforms": [
        "web"
      ],
      "theme": "light",
      "tags": {
        "aesthetic": [
          "minimal",
          "editorial"
        ],
        "mood": [
          "calm",
          "confident"
        ],
        "stack": [
          "react-antd-tailwind"
        ]
      },
      "uses": [
        "blocks/nav/glass-pill-navbar",
        "blocks/form/profile-edit-form",
        "components/buttons/dark-primary-cta",
        "tokens/palettes/skillhub-teal-mist"
      ],
      "preview": "/preview/pages/form-flow/profile-edit",
      "usedBy": [
        "styles/community-social/skillhub-soft-modernist"
      ],
      "hasPreviewFile": true,
      "skillPath": "pages/form-flow/profile-edit/README.md"
    },
    {
      "id": "pages/form-flow/skill-publish-wizard",
      "type": "page",
      "name": "技能发布向导",
      "description": "3 步向导（添加来源 → 预览确认 → 完成）· 拖拽 / URL / 归档上传 · 实时校验",
      "platforms": [
        "web"
      ],
      "theme": "light",
      "tags": {
        "aesthetic": [
          "minimal",
          "editorial"
        ],
        "mood": [
          "calm",
          "confident"
        ],
        "stack": [
          "react-antd-tailwind"
        ]
      },
      "uses": [
        "blocks/nav/glass-pill-navbar",
        "components/buttons/dark-primary-cta",
        "components/inputs/soft-form-input",
        "tokens/palettes/skillhub-teal-mist",
        "tokens/motion/gentle-flow"
      ],
      "preview": "/preview/pages/form-flow/skill-publish-wizard",
      "usedBy": [
        "styles/community-social/skillhub-soft-modernist"
      ],
      "hasPreviewFile": true,
      "skillPath": "pages/form-flow/skill-publish-wizard/README.md"
    },
    {
      "id": "pages/landing/saas-landing",
      "type": "page",
      "name": "SaaS 落地页",
      "description": "标准 SaaS 落地页骨架：Hero / Feature Grid / Pricing / CTA",
      "platforms": [
        "web"
      ],
      "theme": "both",
      "tags": {
        "aesthetic": [
          "minimal"
        ],
        "mood": [
          "serious"
        ],
        "stack": [
          "react-antd-tailwind",
          "html-tailwind"
        ]
      },
      "preview": "/preview/pages/landing/saas-landing",
      "uses": [],
      "usedBy": [
        "styles/saas-tool/cold-industrial-saas"
      ],
      "hasPreviewFile": true,
      "skillPath": "pages/landing/saas-landing/README.md"
    },
    {
      "id": "pages/landing/skill-community-home",
      "type": "page",
      "name": "技能社区首页",
      "description": "Hero 流光 → TOP 榜单 → 分类图标导航 → 搜索 → Skill 网格 + 分页",
      "platforms": [
        "web"
      ],
      "theme": "light",
      "tags": {
        "aesthetic": [
          "minimal",
          "editorial"
        ],
        "mood": [
          "calm",
          "confident"
        ],
        "stack": [
          "react-antd-tailwind"
        ]
      },
      "uses": [
        "blocks/nav/glass-pill-navbar",
        "blocks/marketing/gradient-hero",
        "blocks/display/leaderboard-row",
        "blocks/display/skill-card",
        "components/tags-badges/teal-pill",
        "components/avatars-icons/letter-avatar",
        "tokens/palettes/skillhub-teal-mist",
        "tokens/typography/pairs/inter-jetbrains-duo",
        "tokens/motion/gentle-flow"
      ],
      "preview": "/preview/pages/landing/skill-community-home",
      "usedBy": [
        "styles/community-social/skillhub-soft-modernist"
      ],
      "hasPreviewFile": true,
      "skillPath": "pages/landing/skill-community-home/README.md"
    },
    {
      "id": "pages/list-table/admin-console",
      "type": "page",
      "name": "多域管理后台",
      "description": "Tabs 切多个管理域 + 每 Tab 里 toolbar-bar + table 的标准列表页",
      "platforms": [
        "web"
      ],
      "theme": "light",
      "tags": {
        "aesthetic": [
          "minimal",
          "editorial"
        ],
        "mood": [
          "calm",
          "confident"
        ],
        "stack": [
          "react-antd-tailwind"
        ]
      },
      "uses": [
        "blocks/nav/glass-pill-navbar",
        "blocks/layout/toolbar-bar",
        "blocks/display/table",
        "tokens/palettes/skillhub-teal-mist",
        "tokens/typography/pairs/inter-jetbrains-duo"
      ],
      "preview": "/preview/pages/list-table/admin-console",
      "usedBy": [
        "styles/community-social/skillhub-soft-modernist"
      ],
      "hasPreviewFile": true,
      "skillPath": "pages/list-table/admin-console/README.md"
    },
    {
      "id": "pages/list-table/practice-plaza",
      "type": "page",
      "name": "实践广场",
      "description": "紧凑 hero + 排序切换 + 过滤胶囊 + 帖子卡列表 + 榜单侧栏",
      "platforms": [
        "web"
      ],
      "theme": "light",
      "tags": {
        "aesthetic": [
          "minimal",
          "editorial"
        ],
        "mood": [
          "calm",
          "confident"
        ],
        "stack": [
          "react-antd-tailwind"
        ]
      },
      "uses": [
        "blocks/nav/glass-pill-navbar",
        "blocks/display/leaderboard-row",
        "blocks/feedback/empty-state",
        "components/buttons/dark-primary-cta",
        "components/avatars-icons/letter-avatar",
        "components/tags-badges/teal-pill",
        "tokens/palettes/skillhub-teal-mist"
      ],
      "preview": "/preview/pages/list-table/practice-plaza",
      "usedBy": [
        "styles/community-social/skillhub-soft-modernist"
      ],
      "hasPreviewFile": true,
      "skillPath": "pages/list-table/practice-plaza/README.md"
    },
    {
      "id": "products/acme-cold-saas",
      "type": "product",
      "name": "Acme · 冷感工业 SaaS",
      "description": "为量化团队打造的效率驾驶舱——密集表格、等宽数字、无暖色装饰。",
      "platforms": [
        "web"
      ],
      "theme": "dark",
      "category": "productivity",
      "refs": {
        "style": "styles/saas-tool/cold-industrial-saas",
        "pages": [
          "pages/landing/saas-landing"
        ],
        "blocks": [
          "blocks/layout/toolbar-bar",
          "blocks/display/table"
        ],
        "components": [
          "components/buttons/ghost-button"
        ],
        "tokens": {
          "palette": "tokens/palettes/slate-cyan-ice",
          "typography": "tokens/typography/pairs/ibm-plex-duo"
        }
      },
      "tags": {
        "aesthetic": [
          "minimal",
          "industrial"
        ],
        "mood": [
          "cold",
          "serious"
        ],
        "stack": [
          "react-antd-tailwind"
        ]
      },
      "uses": [],
      "usedBy": [],
      "hasPreviewFile": false,
      "skillPath": "products/acme-cold-saas/README.md"
    },
    {
      "id": "products/skillhub",
      "type": "product",
      "name": "SkillHub · AI 技能社区平台",
      "description": "聚合 Git 仓库扫描 SKILL.md 的技能发现、投稿、实践与管理平台",
      "platforms": [
        "web"
      ],
      "theme": "light",
      "category": "productivity",
      "refs": {
        "style": "styles/community-social/skillhub-soft-modernist",
        "pages": [
          "pages/landing/skill-community-home",
          "pages/detail/skill-article-detail",
          "pages/form-flow/skill-publish-wizard",
          "pages/list-table/practice-plaza",
          "pages/detail/practice-post-detail",
          "pages/form-flow/practice-compose",
          "pages/content-reader/im-conversation",
          "pages/dashboard/user-home",
          "pages/form-flow/profile-edit",
          "pages/detail/user-public-profile",
          "pages/auth/auth-split",
          "pages/list-table/admin-console",
          "pages/dashboard/admin-overview"
        ],
        "blocks": [
          "blocks/nav/glass-pill-navbar",
          "blocks/marketing/gradient-hero",
          "blocks/display/skill-card",
          "blocks/display/leaderboard-row",
          "blocks/display/gradient-stat-card",
          "blocks/display/table",
          "blocks/layout/toolbar-bar",
          "blocks/form/auth-split-form",
          "blocks/form/profile-edit-form",
          "blocks/feedback/skeleton-card",
          "blocks/feedback/empty-state"
        ],
        "components": [
          "components/buttons/dark-primary-cta",
          "components/buttons/border-trace-cta",
          "components/inputs/soft-form-input",
          "components/tags-badges/teal-pill",
          "components/avatars-icons/letter-avatar",
          "components/indicators/pulse-dot"
        ],
        "tokens": {
          "palette": "tokens/palettes/skillhub-teal-mist",
          "typography": "tokens/typography/pairs/inter-jetbrains-duo",
          "motion": "tokens/motion/gentle-flow",
          "shadow": "tokens/shadow/ambient-float"
        }
      },
      "tags": {
        "aesthetic": [
          "minimal",
          "editorial"
        ],
        "mood": [
          "calm",
          "confident"
        ],
        "stack": [
          "react-antd-tailwind"
        ]
      },
      "uses": [],
      "usedBy": [],
      "hasPreviewFile": false,
      "skillPath": "products/skillhub/README.md"
    },
    {
      "id": "styles/community-social/skillhub-soft-modernist",
      "type": "style",
      "name": "SkillHub 柔雾现代风",
      "description": "浅色底 + teal 主色 + 玻璃 pill 导航 + 彩虹流光 + 12 色柔和头像 + framer-motion 微动，社区 × 工具双重气质",
      "platforms": [
        "web"
      ],
      "theme": "light",
      "tags": {
        "aesthetic": [
          "minimal",
          "editorial"
        ],
        "mood": [
          "calm",
          "confident"
        ],
        "stack": [
          "react-antd-tailwind"
        ]
      },
      "uses": [
        "tokens/palettes/skillhub-teal-mist",
        "tokens/typography/pairs/inter-jetbrains-duo",
        "tokens/motion/gentle-flow",
        "tokens/shadow/ambient-float",
        "components/buttons/dark-primary-cta",
        "components/buttons/border-trace-cta",
        "components/inputs/soft-form-input",
        "components/tags-badges/teal-pill",
        "components/avatars-icons/letter-avatar",
        "components/indicators/pulse-dot",
        "blocks/nav/glass-pill-navbar",
        "blocks/marketing/gradient-hero",
        "blocks/display/skill-card",
        "blocks/display/leaderboard-row",
        "blocks/display/gradient-stat-card",
        "blocks/display/table",
        "blocks/layout/toolbar-bar",
        "blocks/form/auth-split-form",
        "blocks/form/profile-edit-form",
        "blocks/feedback/skeleton-card",
        "blocks/feedback/empty-state",
        "pages/landing/skill-community-home",
        "pages/detail/skill-article-detail",
        "pages/form-flow/skill-publish-wizard",
        "pages/list-table/practice-plaza",
        "pages/detail/practice-post-detail",
        "pages/form-flow/practice-compose",
        "pages/content-reader/im-conversation",
        "pages/dashboard/user-home",
        "pages/form-flow/profile-edit",
        "pages/detail/user-public-profile",
        "pages/auth/auth-split",
        "pages/list-table/admin-console",
        "pages/dashboard/admin-overview"
      ],
      "preview": "/preview/styles/community-social/skillhub-soft-modernist",
      "usedBy": [],
      "hasPreviewFile": true,
      "skillPath": "styles/community-social/skillhub-soft-modernist/README.md"
    },
    {
      "id": "styles/saas-tool/cold-industrial-saas",
      "type": "style",
      "name": "冷感工业 SaaS",
      "description": "冷感留白 + IBM Plex 双字体 + 几何切割，工具型 SaaS 的整站调性",
      "platforms": [
        "web"
      ],
      "theme": "both",
      "tags": {
        "aesthetic": [
          "minimal",
          "industrial"
        ],
        "mood": [
          "cold",
          "serious"
        ],
        "stack": [
          "react-antd-tailwind"
        ]
      },
      "uses": [
        "tokens/palettes/slate-cyan-ice",
        "tokens/typography/pairs/ibm-plex-duo",
        "components/buttons/ghost-button",
        "pages/landing/saas-landing"
      ],
      "preview": "/preview/styles/saas-tool/cold-industrial-saas",
      "usedBy": [],
      "hasPreviewFile": true,
      "skillPath": "styles/saas-tool/cold-industrial-saas/README.md"
    },
    {
      "id": "tokens/layout/auto-fit-fluid",
      "type": "token",
      "name": "弹性自适应栅格",
      "description": "auto-fit + minmax(min, 1fr) · 永远填行 · 卡宽随数据量与容器宽度浮动",
      "platforms": [
        "web"
      ],
      "theme": "both",
      "tags": {
        "aesthetic": [
          "minimal",
          "editorial"
        ],
        "mood": [
          "calm",
          "confident"
        ],
        "stack": [
          "react-antd-tailwind"
        ]
      },
      "uses": [],
      "preview": "/preview/tokens/layout/auto-fit-fluid",
      "usedBy": [],
      "hasPreviewFile": true,
      "skillPath": "tokens/layout/auto-fit-fluid.md"
    },
    {
      "id": "tokens/layout/fixed-cols-row",
      "type": "token",
      "name": "断点列数 · 一行快照栅格",
      "description": "useCols + slice(0, cols) · 列数 = 显示数 · 卡宽在同屏下恒定不受数据量影响",
      "platforms": [
        "web"
      ],
      "theme": "both",
      "tags": {
        "aesthetic": [
          "minimal",
          "editorial"
        ],
        "mood": [
          "calm",
          "confident"
        ],
        "stack": [
          "react-antd-tailwind"
        ]
      },
      "uses": [],
      "preview": "/preview/tokens/layout/fixed-cols-row",
      "usedBy": [],
      "hasPreviewFile": true,
      "skillPath": "tokens/layout/fixed-cols-row.md"
    },
    {
      "id": "tokens/motion/gentle-flow",
      "type": "token",
      "name": "温和流动动效系统",
      "description": "framer-motion 入场 + hover 浮起 + active 缩放 + CSS 关键帧流光 + SVG 追光",
      "platforms": [
        "web"
      ],
      "theme": "light",
      "tags": {
        "aesthetic": [
          "minimal",
          "editorial"
        ],
        "mood": [
          "calm",
          "confident"
        ],
        "stack": [
          "react-antd-tailwind"
        ]
      },
      "uses": [],
      "preview": "/preview/tokens/motion/gentle-flow",
      "usedBy": [
        "blocks/display/leaderboard-row",
        "blocks/display/skill-card",
        "blocks/feedback/skeleton-card",
        "blocks/marketing/gradient-hero",
        "components/buttons/border-trace-cta",
        "styles/community-social/skillhub-soft-modernist",
        "pages/landing/skill-community-home",
        "pages/form-flow/skill-publish-wizard"
      ],
      "hasPreviewFile": true,
      "skillPath": "tokens/motion/gentle-flow.md"
    },
    {
      "id": "tokens/palettes/skillhub-teal-mist",
      "type": "token",
      "name": "SkillHub 柔雾 Teal 调色板",
      "description": "Teal 主色 50-900 + Slate 中性 + 12 色柔和头像板 + Top3 红黄蓝 + 四色流动渐变",
      "platforms": [
        "web"
      ],
      "theme": "light",
      "tags": {
        "aesthetic": [
          "minimal",
          "editorial"
        ],
        "mood": [
          "calm",
          "confident"
        ],
        "stack": [
          "react-antd-tailwind"
        ]
      },
      "uses": [],
      "preview": "/preview/tokens/palettes/skillhub-teal-mist",
      "usedBy": [
        "blocks/display/gradient-stat-card",
        "blocks/display/leaderboard-row",
        "blocks/display/skill-card",
        "blocks/feedback/empty-state",
        "blocks/feedback/skeleton-card",
        "blocks/marketing/gradient-hero",
        "blocks/nav/glass-pill-navbar",
        "components/avatars-icons/letter-avatar",
        "blocks/form/auth-split-form",
        "blocks/form/profile-edit-form",
        "components/buttons/border-trace-cta",
        "components/buttons/dark-primary-cta",
        "components/indicators/pulse-dot",
        "components/inputs/soft-form-input",
        "components/tags-badges/teal-pill",
        "styles/community-social/skillhub-soft-modernist",
        "pages/content-reader/im-conversation",
        "pages/dashboard/admin-overview",
        "pages/auth/auth-split",
        "pages/dashboard/user-home",
        "pages/detail/user-public-profile",
        "pages/form-flow/profile-edit",
        "pages/landing/skill-community-home",
        "pages/list-table/admin-console",
        "pages/list-table/practice-plaza",
        "pages/detail/skill-article-detail",
        "pages/form-flow/skill-publish-wizard"
      ],
      "hasPreviewFile": true,
      "skillPath": "tokens/palettes/skillhub-teal-mist.md"
    },
    {
      "id": "tokens/palettes/slate-cyan-ice",
      "type": "token",
      "name": "Slate × Cyan Ice",
      "description": "冷感留白、深 slate 底 + cyan 高亮的工具型界面基础色",
      "platforms": [
        "any"
      ],
      "theme": "both",
      "tags": {
        "aesthetic": [
          "minimal",
          "industrial"
        ],
        "mood": [
          "cold",
          "serious"
        ],
        "stack": [
          "react-antd-tailwind",
          "html-tailwind"
        ]
      },
      "preview": "/preview/tokens/palettes/slate-cyan-ice",
      "uses": [],
      "usedBy": [
        "components/buttons/ghost-button",
        "styles/saas-tool/cold-industrial-saas"
      ],
      "hasPreviewFile": true,
      "skillPath": "tokens/palettes/slate-cyan-ice.md"
    },
    {
      "id": "tokens/shadow/ambient-float",
      "type": "token",
      "name": "环境悬浮阴影",
      "description": "超轻环境阴影（≤0.04 透明度）+ hover:shadow-md 浮起 + 脉冲辉光",
      "platforms": [
        "web"
      ],
      "theme": "light",
      "tags": {
        "aesthetic": [
          "minimal",
          "editorial"
        ],
        "mood": [
          "calm",
          "confident"
        ],
        "stack": [
          "react-antd-tailwind"
        ]
      },
      "uses": [],
      "preview": "/preview/tokens/shadow/ambient-float",
      "usedBy": [
        "blocks/display/gradient-stat-card",
        "blocks/display/skill-card",
        "blocks/nav/glass-pill-navbar",
        "components/indicators/pulse-dot",
        "styles/community-social/skillhub-soft-modernist"
      ],
      "hasPreviewFile": true,
      "skillPath": "tokens/shadow/ambient-float.md"
    },
    {
      "id": "tokens/typography/pairs/ibm-plex-duo",
      "type": "token",
      "name": "IBM Plex 双字体",
      "description": "IBM Plex Sans + IBM Plex Mono，技术感与中性感兼具的字体搭配",
      "platforms": [
        "any"
      ],
      "theme": "both",
      "tags": {
        "aesthetic": [
          "minimal",
          "industrial"
        ],
        "mood": [
          "serious",
          "calm"
        ],
        "stack": [
          "react-antd-tailwind",
          "html-tailwind"
        ]
      },
      "preview": "/preview/tokens/typography/pairs/ibm-plex-duo",
      "uses": [],
      "usedBy": [
        "styles/saas-tool/cold-industrial-saas"
      ],
      "hasPreviewFile": true,
      "skillPath": "tokens/typography/pairs/ibm-plex-duo.md"
    },
    {
      "id": "tokens/typography/pairs/inter-jetbrains-duo",
      "type": "token",
      "name": "Inter × JetBrains Mono 字体对",
      "description": "Inter + Space Grotesk 备选（正文）· JetBrains Mono（等宽）· 开启 Inter 现代字形特性",
      "platforms": [
        "web"
      ],
      "theme": "light",
      "tags": {
        "aesthetic": [
          "minimal",
          "editorial"
        ],
        "mood": [
          "calm",
          "confident"
        ],
        "stack": [
          "react-antd-tailwind"
        ]
      },
      "uses": [],
      "preview": "/preview/tokens/typography/pairs/inter-jetbrains-duo",
      "usedBy": [
        "blocks/marketing/gradient-hero",
        "blocks/form/auth-split-form",
        "styles/community-social/skillhub-soft-modernist",
        "pages/dashboard/admin-overview",
        "pages/auth/auth-split",
        "pages/detail/practice-post-detail",
        "pages/form-flow/practice-compose",
        "pages/landing/skill-community-home",
        "pages/list-table/admin-console",
        "pages/detail/skill-article-detail"
      ],
      "hasPreviewFile": true,
      "skillPath": "tokens/typography/pairs/inter-jetbrains-duo.md"
    }
  ]
}
